skycastle/__init__.py
skycastle/__main__.py
skycastle/game_commands/interaction.py
skycastle/game_commands/main_handler.py
skycastle/game_commands/navigation.py
skycastle/game_commands/puzzles.py
skycastle/game_commands/system.py
skycastle/gamestate.py
skycastle/save_manager.py
skycastle/ui.py
skycastle/worlddata.py
skycastle-0.1.5.dist-info/METADATA
skycastle-0.1.5.dist-info/WHEEL
skycastle-0.1.5.dist-info/entry_points.txt
skycastle-0.1.5.dist-info/RECORD
