Metadata-Version: 2.3
Name: skycastle
Version: 0.1.5
Summary: A command-line text adventure where a young boy explores a fantastical, cloud-borne castle to find his lost father.
License: MIT
Author: mindfilleter
Requires-Python: >=3.8,<4.0
Classifier: License :: OSI Approved :: MIT License
Classifier: Programming Language :: Python :: 3
Classifier: Programming Language :: Python :: 3.8
Classifier: Programming Language :: Python :: 3.9
Classifier: Programming Language :: Python :: 3.10
Classifier: Programming Language :: Python :: 3.11
Classifier: Programming Language :: Python :: 3.12
Classifier: Programming Language :: Python :: 3.13
Requires-Dist: colorama (>=0.4.6,<0.5.0)
Project-URL: Homepage, https://github.com/mindfilleter/skycastle
Project-URL: Repository, https://github.com/mindfilleter/skycastle
